<?xml version="1.0" encoding="us-ascii"?>
<root>
  <gameObject objectName="WideWallCollider (3)" objectAsset="WideWallCollider">
    <transform>
      <position x="-3" y="4753.74" z="1.278822" />
      <rotation x="0" y="180" z="0" />
      <scale x="1" y="1.257136" z="1" />
      <Tag tag="Left" />
      <Layer layer="19" />
      <colliderCenter x="-0.3173242" y="7.686629" z="-1.549721E-06" />
      <colliderSize x="1" y="15.366" z="1" />
    </transform>
  </gameObject>
  <gameObject objectName="pingguo (43)" objectAsset="shoulijian">
    <transform>
      <position x="-0.73" y="4757.78" z="1" />
      <rotation x="90" y="180" z="0" />
      <scale x="1" y="1" z="1" />
      <Tag tag="Untagged" />
      <Layer layer="13" />
    </transform>
  </gameObject>
  <gameObject objectName="chengzi (34)" objectAsset="shoulijian">
    <transform>
      <position x="-0.29" y="4765.8" z="1" />
      <rotation x="90" y="180" z="0" />
      <scale x="1" y="1" z="1" />
      <Tag tag="Untagged" />
      <Layer layer="13" />
    </transform>
  </gameObject>
  <gameObject objectName="Dyn_tanhuang (9)" objectAsset="Dyn_tanhuang">
    <transform>
      <position x="3.380847" y="4751.103" z="1.200021" />
      <rotation x="2.504478E-06" y="0" z="0" />
      <scale x="-1" y="0.8" z="0.8" />
      <Tag tag="Right" />
      <Layer layer="11" />
    </transform>
  </gameObject>
  <gameObject objectName="pingguo (42)" objectAsset="shoulijian">
    <transform>
      <position x="0.25" y="4757.45" z="1" />
      <rotation x="90" y="180" z="0" />
      <scale x="1" y="1" z="1" />
      <Tag tag="Untagged" />
      <Layer layer="13" />
    </transform>
  </gameObject>
  <gameObject objectName="Obj_tengwan03 (9)" objectAsset="Obj_tengwan03">
    <transform>
      <position x="3.33" y="4738.7" z="1.24" />
      <rotation x="2.504477E-06" y="272.2552" z="1.323111E-12" />
      <scale x="1" y="1" z="1" />
      <Tag tag="Right" />
      <Layer layer="0" />
    </transform>
  </gameObject>
  <gameObject objectName="Dyn_zhangai01 (40)" objectAsset="Obstacle_zhangai01">
    <transform>
      <position x="2.43" y="4760.495" z="1.200001" />
      <rotation x="-84" y="0" z="-180" />
      <scale x="10" y="10" z="10" />
      <Tag tag="Right" />
      <Layer layer="10" />
    </transform>
  </gameObject>
  <gameObject objectName="li (15)" objectAsset="shoulijian">
    <transform>
      <position x="-0.3800001" y="4768.391" z="1" />
      <rotation x="90" y="180" z="0" />
      <scale x="1" y="1" z="1" />
      <Tag tag="Untagged" />
      <Layer layer="13" />
    </transform>
  </gameObject>
  <gameObject objectName="mangguo (17)" objectAsset="shoulijian">
    <transform>
      <position x="0.8600001" y="4742.86" z="1" />
      <rotation x="90" y="180" z="0" />
      <scale x="1" y="1" z="1" />
      <Tag tag="Fruit" />
      <Layer layer="13" />
    </transform>
  </gameObject>
  <gameObject objectName="Obj_shudong02" objectAsset="Obj_shudong02">
    <transform>
      <position x="-3.375516" y="4752.911" z="0.8359127" />
      <rotation x="0" y="125.7724" z="0" />
      <scale x="1" y="1" z="1" />
      <Tag tag="Left" />
      <Layer layer="0" />
    </transform>
  </gameObject>
  <gameObject objectName="li (16)" objectAsset="shoulijian">
    <transform>
      <position x="0.5100002" y="4768.01" z="1" />
      <rotation x="90" y="180" z="0" />
      <scale x="1" y="1" z="1" />
      <Tag tag="Untagged" />
      <Layer layer="13" />
    </transform>
  </gameObject>
  <gameObject objectName="li (17)" objectAsset="shoulijian">
    <transform>
      <position x="1.42" y="4767.641" z="1" />
      <rotation x="90" y="180" z="0" />
      <scale x="1" y="1" z="1" />
      <Tag tag="Untagged" />
      <Layer layer="13" />
    </transform>
  </gameObject>
  <gameObject objectName="Obj_shugan (4)" objectAsset="obj_paodaor">
    <transform>
      <position x="3.383086" y="4756.391" z="1.108822" />
      <rotation x="-90" y="-90" z="0" />
      <scale x="1" y="1" z="1" />
      <Tag tag="Right" />
      <Layer layer="8" />
    </transform>
  </gameObject>
  <gameObject objectName="chengzi (33)" objectAsset="shoulijian">
    <transform>
      <position x="-1.24" y="4765.48" z="1" />
      <rotation x="90" y="180" z="0" />
      <scale x="1" y="1" z="1" />
      <Tag tag="Untagged" />
      <Layer layer="13" />
    </transform>
  </gameObject>
  <gameObject objectName="Obj_tengwan04 (1)" objectAsset="Obj_tengwan04">
    <transform>
      <position x="-0.09060955" y="4747.36" z="5.488407" />
      <rotation x="2.504479E-06" y="20.69002" z="2.544444E-13" />
      <scale x="1.630369" y="1.630368" z="1.630368" />
      <Tag tag="Untagged" />
      <Layer layer="0" />
    </transform>
  </gameObject>
  <gameObject objectName="Dyn_tanhuang (20)" objectAsset="Dyn_tanhuang">
    <transform>
      <position x="-3.359154" y="4748.833" z="1.200023" />
      <rotation x="2.504478E-06" y="0" z="0" />
      <scale x="0.8" y="0.8" z="0.8" />
      <Tag tag="Left" />
      <Layer layer="11" />
    </transform>
  </gameObject>
  <gameObject objectName="pingguo (44)" objectAsset="shoulijian">
    <transform>
      <position x="-1.79" y="4758.11" z="1" />
      <rotation x="90" y="180" z="0" />
      <scale x="1" y="1" z="1" />
      <Tag tag="Untagged" />
      <Layer layer="13" />
    </transform>
  </gameObject>
  <gameObject objectName="Obj_zhangai02 (75)" objectAsset="obj_zhangaira_wujin">
    <transform>
      <position x="3.184421" y="4768.161" z="1.238822" />
      <rotation x="0" y="-90" z="0" />
      <scale x="1" y="1" z="1" />
      <Tag tag="Right" />
      <Layer layer="9" />
    </transform>
  </gameObject>
  <gameObject objectName="boluo (24)" objectAsset="shoulijian">
    <transform>
      <position x="1.24" y="4739.541" z="1" />
      <rotation x="90" y="180" z="0" />
      <scale x="1" y="1" z="1" />
      <Tag tag="Untagged" />
      <Layer layer="13" />
    </transform>
  </gameObject>
  <gameObject objectName="chengzi (35)" objectAsset="shoulijian">
    <transform>
      <position x="0.6800003" y="4766.11" z="1" />
      <rotation x="90" y="180" z="0" />
      <scale x="1" y="1" z="1" />
      <Tag tag="Untagged" />
      <Layer layer="13" />
    </transform>
  </gameObject>
  <gameObject objectName="pingguo (41)" objectAsset="shoulijian">
    <transform>
      <position x="1.28" y="4757.161" z="1" />
      <rotation x="90" y="180" z="0" />
      <scale x="1" y="1" z="1" />
      <Tag tag="Untagged" />
      <Layer layer="13" />
    </transform>
  </gameObject>
  <gameObject objectName="boluo (23)" objectAsset="shoulijian">
    <transform>
      <position x="2.24" y="4739.541" z="1" />
      <rotation x="90" y="180" z="0" />
      <scale x="1" y="1" z="1" />
      <Tag tag="Untagged" />
      <Layer layer="13" />
    </transform>
  </gameObject>
  <gameObject objectName="Obj_shengzi (32)" objectAsset="Obj_shengzi">
    <transform>
      <position x="-3.455579" y="4755.851" z="1.108824" />
      <rotation x="2.504478E-06" y="180" z="0" />
      <scale x="-1" y="1" z="1" />
      <Tag tag="Left" />
      <Layer layer="0" />
    </transform>
  </gameObject>
  <gameObject objectName="Obj_shengzi (35)" objectAsset="Obj_shengzi">
    <transform>
      <position x="-3.455579" y="4766.61" z="1.108824" />
      <rotation x="2.504478E-06" y="180" z="0" />
      <scale x="-1" y="1" z="1" />
      <Tag tag="Left" />
      <Layer layer="0" />
    </transform>
  </gameObject>
  <gameObject objectName="chengzi (36)" objectAsset="shoulijian">
    <transform>
      <position x="1.67" y="4766.46" z="1" />
      <rotation x="90" y="180" z="0" />
      <scale x="1" y="1" z="1" />
      <Tag tag="Untagged" />
      <Layer layer="13" />
    </transform>
  </gameObject>
  <gameObject objectName="Obj_shengzi (31)" objectAsset="Obj_shengzi">
    <transform>
      <position x="-3.455579" y="4759.641" z="1.108824" />
      <rotation x="2.504478E-06" y="180" z="0" />
      <scale x="-1" y="1" z="1" />
      <Tag tag="Left" />
      <Layer layer="0" />
    </transform>
  </gameObject>
  <gameObject objectName="huolongguo (20)" objectAsset="shoulijian">
    <transform>
      <position x="-2.5" y="4743.61" z="1" />
      <rotation x="90" y="180" z="0" />
      <scale x="1" y="1" z="1" />
      <Tag tag="Untagged" />
      <Layer layer="13" />
    </transform>
  </gameObject>
  <gameObject objectName="boluo (28)" objectAsset="shoulijian">
    <transform>
      <position x="1.44" y="4751.331" z="1" />
      <rotation x="90" y="180" z="0" />
      <scale x="1" y="1" z="1" />
      <Tag tag="Untagged" />
      <Layer layer="13" />
    </transform>
  </gameObject>
  <gameObject objectName="Obj_shudong01 (1)" objectAsset="Obj_shudong01">
    <transform>
      <position x="3.577484" y="4746.03" z="0.7509108" />
      <rotation x="0" y="234.0609" z="0" />
      <scale x="1" y="1" z="1" />
      <Tag tag="Right" />
      <Layer layer="0" />
    </transform>
  </gameObject>
  <gameObject objectName="shuimitao (27)" objectAsset="shoulijian">
    <transform>
      <position x="-0.8199997" y="4747.931" z="1" />
      <rotation x="90" y="180" z="0" />
      <scale x="1" y="1" z="1" />
      <Tag tag="Untagged" />
      <Layer layer="13" />
    </transform>
  </gameObject>
  <gameObject objectName="Obj_tengwan03 (4)" objectAsset="Obj_tengwan03">
    <transform>
      <position x="3.33" y="4756.05" z="1.24" />
      <rotation x="2.504477E-06" y="272.2552" z="1.323111E-12" />
      <scale x="1" y="1" z="1" />
      <Tag tag="Right" />
      <Layer layer="0" />
    </transform>
  </gameObject>
  <gameObject objectName="boluo (31)" objectAsset="shoulijian">
    <transform>
      <position x="-1.65" y="4752.371" z="1" />
      <rotation x="90" y="180" z="0" />
      <scale x="1" y="1" z="1" />
      <Tag tag="Untagged" />
      <Layer layer="13" />
    </transform>
  </gameObject>
  <gameObject objectName="huolongguo (19)" objectAsset="shoulijian">
    <transform>
      <position x="-1.69" y="4743.05" z="1" />
      <rotation x="90" y="180" z="0" />
      <scale x="1" y="1" z="1" />
      <Tag tag="Untagged" />
      <Layer layer="13" />
    </transform>
  </gameObject>
  <gameObject objectName="boluo (26)" objectAsset="shoulijian">
    <transform>
      <position x="-0.7399998" y="4739.541" z="1" />
      <rotation x="90" y="180" z="0" />
      <scale x="1" y="1" z="1" />
      <Tag tag="Untagged" />
      <Layer layer="13" />
    </transform>
  </gameObject>
  <gameObject objectName="mangguo (19)" objectAsset="shoulijian">
    <transform>
      <position x="2.78" y="4744.041" z="1" />
      <rotation x="90" y="180" z="0" />
      <scale x="1" y="1" z="1" />
      <Tag tag="Fruit" />
      <Layer layer="13" />
    </transform>
  </gameObject>
  <gameObject objectName="Obj_mogu01 (5)" objectAsset="Obj_mogu01">
    <transform>
      <position x="-3.695516" y="4764.67" z="1.975913" />
      <rotation x="2.504481E-06" y="2.227784" z="2.449027E-13" />
      <scale x="0.7475738" y="0.7475736" z="0.7475738" />
      <Tag tag="Untagged" />
      <Layer layer="0" />
    </transform>
  </gameObject>
  <gameObject objectName="Obj_shengzi (33)" objectAsset="Obj_shengzi">
    <transform>
      <position x="-3.455579" y="4762.871" z="1.108824" />
      <rotation x="2.504478E-06" y="180" z="0" />
      <scale x="-1" y="1" z="1" />
      <Tag tag="Left" />
      <Layer layer="0" />
    </transform>
  </gameObject>
  <gameObject objectName="boluo (30)" objectAsset="shoulijian">
    <transform>
      <position x="-0.6700001" y="4751.99" z="1" />
      <rotation x="90" y="180" z="0" />
      <scale x="1" y="1" z="1" />
      <Tag tag="Untagged" />
      <Layer layer="13" />
    </transform>
  </gameObject>
  <gameObject objectName="Dyn_tanhuang (13)" objectAsset="Dyn_tanhuang">
    <transform>
      <position x="3.380847" y="4767.272" z="1.200021" />
      <rotation x="2.504478E-06" y="0" z="0" />
      <scale x="-1" y="0.8" z="0.8" />
      <Tag tag="Right" />
      <Layer layer="11" />
    </transform>
  </gameObject>
  <gameObject objectName="shuimitao (28)" objectAsset="shoulijian">
    <transform>
      <position x="0.1900001" y="4747.791" z="1" />
      <rotation x="90" y="180" z="0" />
      <scale x="1" y="1" z="1" />
      <Tag tag="Untagged" />
      <Layer layer="13" />
    </transform>
  </gameObject>
  <gameObject objectName="huolongguo (17)" objectAsset="shoulijian">
    <transform>
      <position x="-0.1099997" y="4741.96" z="1" />
      <rotation x="90" y="180" z="0" />
      <scale x="1" y="1" z="1" />
      <Tag tag="Untagged" />
      <Layer layer="13" />
    </transform>
  </gameObject>
  <gameObject objectName="Obj_tengwan04 (3)" objectAsset="Obj_tengwan04">
    <transform>
      <position x="-0.335515" y="4751.86" z="5.015913" />
      <rotation x="349.366" y="334.9185" z="338.4821" />
      <scale x="1.891231" y="1.89123" z="1.891231" />
      <Tag tag="Untagged" />
      <Layer layer="0" />
    </transform>
  </gameObject>
  <gameObject objectName="Obj_shugan (7)" objectAsset="obj_paodaol">
    <transform>
      <position x="-3.256914" y="4756.22" z="1.108825" />
      <rotation x="-90" y="-90" z="0" />
      <scale x="1" y="1" z="1" />
      <Tag tag="Left" />
      <Layer layer="8" />
    </transform>
  </gameObject>
  <gameObject objectName="shuimitao (29)" objectAsset="shoulijian">
    <transform>
      <position x="1.14" y="4747.61" z="1" />
      <rotation x="90" y="180" z="0" />
      <scale x="1" y="1" z="1" />
      <Tag tag="Untagged" />
      <Layer layer="13" />
    </transform>
  </gameObject>
  <gameObject objectName="huolongguo (18)" objectAsset="shoulijian">
    <transform>
      <position x="-0.98" y="4742.47" z="1" />
      <rotation x="90" y="180" z="0" />
      <scale x="1" y="1" z="1" />
      <Tag tag="Untagged" />
      <Layer layer="13" />
    </transform>
  </gameObject>
  <gameObject objectName="shuimitao (26)" objectAsset="shoulijian">
    <transform>
      <position x="-1.77" y="4748.141" z="1" />
      <rotation x="90" y="180" z="0" />
      <scale x="1" y="1" z="1" />
      <Tag tag="Untagged" />
      <Layer layer="13" />
    </transform>
  </gameObject>
  <gameObject objectName="boluo (27)" objectAsset="shoulijian">
    <transform>
      <position x="-1.72" y="4739.541" z="1" />
      <rotation x="90" y="180" z="0" />
      <scale x="1" y="1" z="1" />
      <Tag tag="Untagged" />
      <Layer layer="13" />
    </transform>
  </gameObject>
  <gameObject objectName="Obj_shudong01 (4)" objectAsset="Obj_shudong01">
    <transform>
      <position x="-3.475516" y="4741.8" z="0.6859131" />
      <rotation x="0" y="131.0716" z="0" />
      <scale x="1" y="1" z="1" />
      <Tag tag="Left" />
      <Layer layer="0" />
    </transform>
  </gameObject>
  <gameObject objectName="boluo (29)" objectAsset="shoulijian">
    <transform>
      <position x="0.3599997" y="4751.661" z="1" />
      <rotation x="90" y="180" z="0" />
      <scale x="1" y="1" z="1" />
      <Tag tag="Untagged" />
      <Layer layer="13" />
    </transform>
  </gameObject>
  <gameObject objectName="shuimitao (30)" objectAsset="shoulijian">
    <transform>
      <position x="2.14" y="4747.47" z="1" />
      <rotation x="90" y="180" z="0" />
      <scale x="1" y="1" z="1" />
      <Tag tag="Untagged" />
      <Layer layer="13" />
    </transform>
  </gameObject>
  <gameObject objectName="pingguo (40)" objectAsset="shoulijian">
    <transform>
      <position x="2.28" y="4756.86" z="1" />
      <rotation x="90" y="180" z="0" />
      <scale x="1" y="1" z="1" />
      <Tag tag="Untagged" />
      <Layer layer="13" />
    </transform>
  </gameObject>
  <gameObject objectName="Obj_tengwan03 (21)" objectAsset="Obj_tengwan03">
    <transform>
      <position x="-4.25" y="4763.76" z="0.3999996" />
      <rotation x="2.504486E-06" y="186.8904" z="1.310388E-12" />
      <scale x="1" y="1" z="1" />
      <Tag tag="Left" />
      <Layer layer="0" />
    </transform>
  </gameObject>
  <gameObject objectName="mangguo (18)" objectAsset="shoulijian">
    <transform>
      <position x="1.82" y="4743.42" z="1" />
      <rotation x="90" y="180" z="0" />
      <scale x="1" y="1" z="1" />
      <Tag tag="Fruit" />
      <Layer layer="13" />
    </transform>
  </gameObject>
  <gameObject objectName="boluo (25)" objectAsset="shoulijian">
    <transform>
      <position x="0.2600002" y="4739.541" z="1" />
      <rotation x="90" y="180" z="0" />
      <scale x="1" y="1" z="1" />
      <Tag tag="Untagged" />
      <Layer layer="13" />
    </transform>
  </gameObject>
  <gameObject objectName="Obj_lingzhi01 (1)" objectAsset="Obj_lingzhi01">
    <transform>
      <position x="-3.745516" y="4757.079" z="1.025913" />
      <rotation x="2.504485E-06" y="77.32162" z="7.124443E-13" />
      <scale x="0.4999999" y="0.4912273" z="0.4999999" />
      <Tag tag="Left" />
      <Layer layer="0" />
    </transform>
  </gameObject>
  <gameObject objectName="Obj_tengwan03 (15)" objectAsset="Obj_tengwan03">
    <transform>
      <position x="-4.25" y="4748.15" z="0.3999996" />
      <rotation x="2.504486E-06" y="186.8904" z="1.310388E-12" />
      <scale x="1" y="1" z="1" />
      <Tag tag="Left" />
      <Layer layer="0" />
    </transform>
  </gameObject>
  <gameObject objectName="Obj_zhangai02 (41)" objectAsset="obj_zhangaila_wujin">
    <transform>
      <position x="-3.015579" y="4765.61" z="1.238824" />
      <rotation x="0" y="-90" z="0" />
      <scale x="1" y="1" z="1" />
      <Tag tag="Left" />
      <Layer layer="9" />
    </transform>
  </gameObject>
  <gameObject objectName="Obj_zhangai02 (38)" objectAsset="obj_zhangaila_wujin">
    <transform>
      <position x="-3.015579" y="4757.521" z="1.238824" />
      <rotation x="0" y="-90" z="0" />
      <scale x="1" y="1" z="1" />
      <Tag tag="Left" />
      <Layer layer="9" />
    </transform>
  </gameObject>
  <gameObject objectName="Obj_zhangai02 (39)" objectAsset="obj_zhangaila_wujin">
    <transform>
      <position x="-3.015579" y="4761.208" z="1.238824" />
      <rotation x="0" y="-90" z="0" />
      <scale x="1" y="1.172092" z="1" />
      <Tag tag="Left" />
      <Layer layer="9" />
    </transform>
  </gameObject>
  <gameObject objectName="Obj_zhangai02 (35)" objectAsset="obj_zhangaila_wujin">
    <transform>
      <position x="-3.015579" y="4753.771" z="1.238824" />
      <rotation x="0" y="-90" z="0" />
      <scale x="1" y="1" z="1" />
      <Tag tag="Left" />
      <Layer layer="9" />
    </transform>
  </gameObject>
</root>