<?xml version="1.0" encoding="us-ascii"?>
<root>
  <gameObject objectName="li (78)" objectAsset="shoulijian">
    <transform>
      <position x="0.1300001" y="8071.121" z="1" />
      <rotation x="90" y="180" z="0" />
      <scale x="1" y="1" z="1" />
      <Tag tag="Untagged" />
      <Layer layer="13" />
    </transform>
  </gameObject>
  <gameObject objectName="Missile (53)" objectAsset="Missile">
    <transform>
      <position x="-2.078453" y="8079.954" z="1.230156" />
      <rotation x="270.0198" y="0" z="0" />
      <scale x="-0.5976814" y="-0.6160063" z="-0.4372868" />
      <Tag tag="Obstacle" />
      <Layer layer="14" />
    </transform>
  </gameObject>
  <gameObject objectName="li (75)" objectAsset="shoulijian">
    <transform>
      <position x="0.1300001" y="8072.021" z="1" />
      <rotation x="90" y="180" z="0" />
      <scale x="1" y="1" z="1" />
      <Tag tag="Untagged" />
      <Layer layer="13" />
    </transform>
  </gameObject>
  <gameObject objectName="Missile (36)" objectAsset="Missile">
    <transform>
      <position x="-2.078452" y="8077.134" z="1.230156" />
      <rotation x="270.0198" y="0" z="0" />
      <scale x="-0.5976814" y="-0.6160063" z="-0.4372868" />
      <Tag tag="Obstacle" />
      <Layer layer="14" />
    </transform>
  </gameObject>
  <gameObject objectName="li (79)" objectAsset="shoulijian">
    <transform>
      <position x="-0.5900002" y="8071.121" z="1" />
      <rotation x="90" y="180" z="0" />
      <scale x="1" y="1" z="1" />
      <Tag tag="Untagged" />
      <Layer layer="13" />
    </transform>
  </gameObject>
  <gameObject objectName="Obj_shengzi (71)" objectAsset="Obj_shengzi">
    <transform>
      <position x="-3.455579" y="8074.001" z="1.108824" />
      <rotation x="2.504478E-06" y="180" z="0" />
      <scale x="-1" y="1" z="1" />
      <Tag tag="Left" />
      <Layer layer="0" />
    </transform>
  </gameObject>
  <gameObject objectName="li (77)" objectAsset="shoulijian">
    <transform>
      <position x="0.8199997" y="8071.121" z="1" />
      <rotation x="90" y="180" z="0" />
      <scale x="1" y="1" z="1" />
      <Tag tag="Untagged" />
      <Layer layer="13" />
    </transform>
  </gameObject>
  <gameObject objectName="Obj_zhangai02 (77)" objectAsset="obj_zhangaira_wujin">
    <transform>
      <position x="3.184421" y="8072.721" z="1.238822" />
      <rotation x="0" y="-90" z="0" />
      <scale x="1" y="1" z="1" />
      <Tag tag="Right" />
      <Layer layer="9" />
    </transform>
  </gameObject>
  <gameObject objectName="Obj_zhangai02 (78)" objectAsset="obj_zhangaira_wujin">
    <transform>
      <position x="3.184421" y="8075.491" z="1.238822" />
      <rotation x="0" y="-90" z="0" />
      <scale x="1" y="1" z="1" />
      <Tag tag="Right" />
      <Layer layer="9" />
    </transform>
  </gameObject>
  <gameObject objectName="li (55)" objectAsset="shoulijian">
    <transform>
      <position x="-0.5900002" y="8072.021" z="1" />
      <rotation x="90" y="180" z="0" />
      <scale x="1" y="1" z="1" />
      <Tag tag="Untagged" />
      <Layer layer="13" />
    </transform>
  </gameObject>
  <gameObject objectName="li (76)" objectAsset="shoulijian">
    <transform>
      <position x="0.8199997" y="8072.021" z="1" />
      <rotation x="90" y="180" z="0" />
      <scale x="1" y="1" z="1" />
      <Tag tag="Untagged" />
      <Layer layer="13" />
    </transform>
  </gameObject>
  <gameObject objectName="Obj_shugan (16)" objectAsset="obj_paodaol">
    <transform>
      <position x="-3.256914" y="8076.301" z="1.108825" />
      <rotation x="-90" y="-90" z="0" />
      <scale x="1" y="1" z="1" />
      <Tag tag="Left" />
      <Layer layer="8" />
    </transform>
  </gameObject>
  <gameObject objectName="Obj_shengzi (83)" objectAsset="Obj_shengzi">
    <transform>
      <position x="3.610421" y="8074.081" z="1.159822" />
      <rotation x="2.504478E-06" y="180" z="0" />
      <scale x="1" y="1" z="1" />
      <Tag tag="Right" />
      <Layer layer="0" />
    </transform>
  </gameObject>
  <gameObject objectName="Obj_shengzi (67)" objectAsset="Obj_shengzi">
    <transform>
      <position x="-3.455579" y="8069.491" z="1.108824" />
      <rotation x="2.504478E-06" y="180" z="0" />
      <scale x="-1" y="1" z="1" />
      <Tag tag="Left" />
      <Layer layer="0" />
    </transform>
  </gameObject>
  <gameObject objectName="Obj_lvye04 (20)" objectAsset="Obj_lvye04">
    <transform>
      <position x="-2.855515" y="8084.251" z="2.435913" />
      <rotation x="335.2551" y="80.52266" z="315.1698" />
      <scale x="2.048841" y="2.048842" z="2.048842" />
      <Tag tag="Left" />
      <Layer layer="0" />
    </transform>
  </gameObject>
  <gameObject objectName="Obj_lvye04 (12)" objectAsset="Obj_lvye04">
    <transform>
      <position x="-3.155517" y="8096.531" z="-1.204087" />
      <rotation x="338.036" y="50.29664" z="325.7578" />
      <scale x="1.483973" y="1.483974" z="1.483974" />
      <Tag tag="Left" />
      <Layer layer="0" />
    </transform>
  </gameObject>
  <gameObject objectName="Obj_lvye04 (17)" objectAsset="Obj_lvye04">
    <transform>
      <position x="-4.075517" y="8081.911" z="-0.274086" />
      <rotation x="338.036" y="50.29664" z="325.7578" />
      <scale x="2.04884" y="2.048842" z="2.048841" />
      <Tag tag="Left" />
      <Layer layer="0" />
    </transform>
  </gameObject>
  <gameObject objectName="Obj_lvye04 (18)" objectAsset="Obj_lvye04">
    <transform>
      <position x="3.784483" y="8081.911" z="-0.2740889" />
      <rotation x="338.036" y="80.4249" z="325.7578" />
      <scale x="2.048841" y="2.048842" z="2.048841" />
      <Tag tag="Left" />
      <Layer layer="0" />
    </transform>
  </gameObject>
  <gameObject objectName="Obj_shengzi (84)" objectAsset="Obj_shengzi">
    <transform>
      <position x="3.610421" y="8077.551" z="1.159822" />
      <rotation x="2.504478E-06" y="180" z="0" />
      <scale x="1" y="1" z="1" />
      <Tag tag="Right" />
      <Layer layer="0" />
    </transform>
  </gameObject>
  <gameObject objectName="Obj_shugan (15)" objectAsset="obj_paodaor">
    <transform>
      <position x="3.383086" y="8076.251" z="1.108822" />
      <rotation x="-90" y="-90" z="0" />
      <scale x="1" y="1" z="1" />
      <Tag tag="Right" />
      <Layer layer="8" />
    </transform>
  </gameObject>
  <gameObject objectName="Obj_shengzi (82)" objectAsset="Obj_shengzi">
    <transform>
      <position x="3.610421" y="8070.221" z="1.159822" />
      <rotation x="2.504478E-06" y="180" z="0" />
      <scale x="1" y="1" z="1" />
      <Tag tag="Right" />
      <Layer layer="0" />
    </transform>
  </gameObject>
  <gameObject objectName="Missile (52)" objectAsset="Missile">
    <transform>
      <position x="2.301548" y="8077.764" z="1.230156" />
      <rotation x="270.0198" y="0" z="0" />
      <scale x="-0.5976814" y="-0.6160063" z="-0.4372868" />
      <Tag tag="Obstacle" />
      <Layer layer="14" />
    </transform>
  </gameObject>
  <gameObject objectName="Obj_lvye04 (19)" objectAsset="Obj_lvye04">
    <transform>
      <position x="2.404486" y="8084.251" z="2.435911" />
      <rotation x="334.3099" y="83.74344" z="307.6195" />
      <scale x="2.04884" y="2.048842" z="2.048841" />
      <Tag tag="Left" />
      <Layer layer="0" />
    </transform>
  </gameObject>
  <gameObject objectName="Obj_shengzi (77)" objectAsset="Obj_shengzi">
    <transform>
      <position x="-3.455579" y="8077.451" z="1.108824" />
      <rotation x="2.504478E-06" y="180" z="0" />
      <scale x="-1" y="1" z="1" />
      <Tag tag="Left" />
      <Layer layer="0" />
    </transform>
  </gameObject>
  <gameObject objectName="Obj_zhangai02 (85)" objectAsset="obj_zhangaila_wujin">
    <transform>
      <position x="-3.015579" y="8075.441" z="1.238824" />
      <rotation x="0" y="-90" z="0" />
      <scale x="1" y="1.243459" z="1" />
      <Tag tag="Left" />
      <Layer layer="9" />
    </transform>
  </gameObject>
  <gameObject objectName="Obj_zhangai02 (84)" objectAsset="obj_zhangaila_wujin">
    <transform>
      <position x="-3.015579" y="8071.991" z="1.238824" />
      <rotation x="0" y="-90" z="0" />
      <scale x="1" y="1.243459" z="1" />
      <Tag tag="Left" />
      <Layer layer="9" />
    </transform>
  </gameObject>
</root>